[{"_id":2,"name":"The Godfather","description":"The aging patriarch of an organized crime dynasty transfers control of his clandestine empire to his reluctant son.","director":"Francis Ford Coppola","genre":"drama","year":"1972","rating":"9.2","duration":"175"},{"_id":3,"name":"The Godfather","description":"The aging patriarch of an organized crime dynasty transfers control of his clandestine empire to his reluctant son.","director":"Francis Ford Coppola","genre":"drama","year":"1972","rating":"2","duration":"175"},{"_id":4,"name":"The Shawshank Redemption","description":"Two imprisoned men bond over a number of years, finding solace and eventual redemption through acts of common decency.","director":"Frank Darabont","genre":"fantasy","year":"1994","rating":"9.3","duration":"142"},{"_id":5,"name":"The Godfather","description":"The aging patriarch of an organized crime dynasty transfers control of his clandestine empire to his reluctant son.","director":"Francis Ford Coppola","genre":"drama","year":"1972","rating":"9.2","duration":"175"},{"_id":6,"name":"dsdjg;ldjg","description":"fsjgoerjgo;ejrgr;jdf","director":"dsjdlks","genre":"mystery","year":"1214","rating":"124","duration":"124"},{"_id":7,"name":"Pulp Fiction","description":"The lives of two mob hit men, a boxer, a gangster's wife, and a pair of diner bandits intertwine in four tales of violence and redemption.","director":"Quentin Tarantino","genre":"drama","year":"1994","rating":"8.9","duration":"154"},{"_id":8,"name":"","description":"","director":"","genre":"","year":0,"rating":0,"duration":0},{"_id":9,"name":"","description":"","director":"","genre":"","year":0,"rating":0,"duration":0},{"_id":10,"name":"The Shawshank Redemption","description":"Two imprisoned men bond over a number of years, finding solace and eventual redemption through acts of common decency.","director":"Frank Darabont","genre":"fantasy","year":"1994","rating":"9.3","duration":"142"},{"_id":11,"name":"12 Angry Men","description":"A dissenting juror in a murder trial slowly manages to convince the others that the case is not as obviously clear as it seemed in court. ","director":"Sidney Lumet","genre":"drama","year":"1957","rating":"8.9","duration":"96"},{"_id":12,"name":"","description":"","director":"","genre":"","year":0,"rating":0,"duration":0},{"_id":13,"name":"The Shawshank Redemption","description":"Two imprisoned men bond over a number of years, finding solace and eventual redemption through acts of common decency.","director":"Frank Darabont","genre":"fantasy","year":"1994","rating":"9.3","duration":"142"},{"_id":14,"name":"","description":"","director":"","genre":"","year":0,"rating":0,"duration":0},{"_id":15,"name":"Interstellar","description":"A team of explorers travel through a wormhole in space in an attempt to ensure humanity's survival.","director":"Christopher Nolan","genre":"sci-fi","year":"2014","rating":"8.6","duration":"169"},{"_id":16,"name":"Interstellar","description":"A team of explorers travel through a wormhole in space in an attempt to ensure humanity's survival.","director":"Christopher Nolan","genre":"sci-fi","year":"2014","rating":"10","duration":"169"},{"_id":17,"name":"","description":"","director":"","genre":"","year":0,"rating":0,"duration":0},{"_id":18,"name":"wghlrg","description":"gerorjg;sjrg;ljkdl;kgro;sekr;g","director":"fsegsrgjlf","genre":"comedy","year":"2009","rating":"5","duration":"132"},{"_id":19,"name":"lsl;jg;srf","description":"","director":"12sefsg","genre":"mystery","year":"1999","rating":"3","duration":"123"}]